acapy_wallet_groups_plugin/definition.py
acapy_wallet_groups_plugin/v1_0/__init__.py
acapy_wallet_groups_plugin/v1_0/routes.py
acapy_wallet_groups_plugin-1.3.1.post20250702.dist-info/LICENSE.md
acapy_wallet_groups_plugin-1.3.1.post20250702.dist-info/METADATA
acapy_wallet_groups_plugin-1.3.1.post20250702.dist-info/WHEEL
acapy_wallet_groups_plugin-1.3.1.post20250702.dist-info/RECORD
