Metadata-Version: 2.3
Name: acapy_wallet_groups_plugin
Version: 1.3.1.post20250702
Summary: Agent plugin to add a group id to a wallet
Author: Berend Sliedrecht
Author-email: berend@animo.id
Requires-Python: >=3.12.0,<4.0.0
Classifier: Programming Language :: Python :: 3
Classifier: Programming Language :: Python :: 3.12
Classifier: Programming Language :: Python :: 3.13
Requires-Dist: acapy-agent-didx (>=1.3.1.post20250702)
Project-URL: Repository, https://github.com/didx-xyz/acapy-wallet-groups-plugin
